[
	{
		"nroDocumento": "39875555",
		"tipoPersona": {
			"value": "Ambos",
			"label": "Ambos"
		},
		"tipoDocumento": {
			"value": 80,
			"label": "CUIT"
		},
		"idPersona": "",
		"razonSocial": "BANCO SAFRA S.A.",
		"calle": "Av. San Martin",
		"nro": "998",
		"piso": "",
		"depto": "",
		"sector": "",
		"torre": "",
		"manzana": "",
		"localidad": "CABA",
		"codigoPostal": "",
		"nombreContacto": "Reinaldo Pepe",
		"email": "pepe@gmail.com",
		"telefono": "47484748",
		"nroIngBruto": "",
		"dateStart": "",
		"gln": "",
		"codigoInterno": "",
		"estado": true
	},
	{
		"nroDocumento": "39875570",
		"tipoPersona": "",
		"tipoDocumento": {
			"value": 80,
			"label": "CUIT"
		},
		"idPersona": "",
		"razonSocial": "BANCO SAFRA S.A.",
		"calle": "Av. San Martin",
		"nro": "998",
		"piso": "",
		"depto": "",
		"sector": "",
		"torre": "",
		"manzana": "",
		"localidad": "CABA",
		"codigoPostal": "",
		"nombreContacto": "Reinaldo Pepe",
		"email": "pepe@gmail.com",
		"telefono": "47484748",
		"nroIngBruto": "",
		"dateStart": "",
		"gln": "",
		"codigoInterno": "",
		"estado": true
	},
	{
		"nroDocumento": "39875571",
		"tipoPersona": "",
		"tipoDocumento": {
			"value": 80,
			"label": "CUIT"
		},
		"idPersona": "",
		"razonSocial": "BANCO SAFRA S.A.",
		"calle": "Av. San Martin",
		"nro": "998",
		"piso": "",
		"depto": "",
		"sector": "",
		"torre": "",
		"manzana": "",
		"localidad": "CABA",
		"codigoPostal": "",
		"nombreContacto": "Reinaldo Pepe",
		"email": "pepe@gmail.com",
		"telefono": "47484748",
		"nroIngBruto": "",
		"dateStart": "",
		"gln": "",
		"codigoInterno": "",
		"estado": true
	},
	{
		"nroDocumento": "39875572",
		"tipoPersona": "",
		"tipoDocumento": {
			"value": 80,
			"label": "CUIT"
		},
		"idPersona": "",
		"razonSocial": "BANCO SAFRA S.A.",
		"calle": "Av. San Martin",
		"nro": "998",
		"piso": "",
		"depto": "",
		"sector": "",
		"torre": "",
		"manzana": "",
		"localidad": "CABA",
		"codigoPostal": "",
		"nombreContacto": "Reinaldo Pepe",
		"email": "pepe@gmail.com",
		"telefono": "47484748",
		"nroIngBruto": "",
		"dateStart": "",
		"gln": "",
		"codigoInterno": "",
		"estado": false
	},
	{
		"nroDocumento": "39875573",
		"tipoPersona": "",
		"tipoDocumento": {
			"value": 80,
			"label": "CUIT"
		},
		"idPersona": "",
		"razonSocial": "BANCO SAFRA S.A.",
		"calle": "Av. San Martin",
		"nro": "998",
		"piso": "",
		"depto": "",
		"sector": "",
		"torre": "",
		"manzana": "",
		"localidad": "CABA",
		"codigoPostal": "",
		"nombreContacto": "Reinaldo Pepe",
		"email": "pepe@gmail.com",
		"telefono": "47484748",
		"nroIngBruto": "",
		"dateStart": "",
		"gln": "",
		"codigoInterno": "",
		"estado": true
	},
	{
		"nroDocumento": "39875574",
		"tipoPersona": "",
		"tipoDocumento": {
			"value": 80,
			"label": "CUIT"
		},
		"idPersona": "",
		"razonSocial": "BANCO SAFRA S.A.",
		"calle": "Av. San Martin",
		"nro": "998",
		"piso": "",
		"depto": "",
		"sector": "",
		"torre": "",
		"manzana": "",
		"localidad": "CABA",
		"codigoPostal": "",
		"nombreContacto": "Reinaldo Pepe",
		"email": "pepe@gmail.com",
		"telefono": "47484748",
		"nroIngBruto": "",
		"dateStart": "",
		"gln": "",
		"codigoInterno": "",
		"estado": false
	},
	{
		"nroDocumento": "39875575",
		"tipoPersona": "",
		"tipoDocumento": {
			"value": 80,
			"label": "CUIT"
		},
		"idPersona": "",
		"razonSocial": "BANCO SAFRA S.A.",
		"calle": "Av. San Martin",
		"nro": "998",
		"piso": "",
		"depto": "",
		"sector": "",
		"torre": "",
		"manzana": "",
		"localidad": "CABA",
		"codigoPostal": "",
		"nombreContacto": "Reinaldo Pepe",
		"email": "pepe@gmail.com",
		"telefono": "47484748",
		"nroIngBruto": "",
		"dateStart": "",
		"gln": "",
		"codigoInterno": "",
		"estado": true
	},
	{
		"nroDocumento": "39875576",
		"tipoPersona": "",
		"tipoDocumento": {
			"value": 80,
			"label": "CUIT"
		},
		"idPersona": "",
		"razonSocial": "BANCO SAFRA S.A.",
		"calle": "Av. San Martin",
		"nro": "998",
		"piso": "",
		"depto": "",
		"sector": "",
		"torre": "",
		"manzana": "",
		"localidad": "CABA",
		"codigoPostal": "",
		"nombreContacto": "Reinaldo Pepe",
		"email": "pepe@gmail.com",
		"telefono": "47484748",
		"nroIngBruto": "",
		"dateStart": "",
		"gln": "",
		"codigoInterno": "",
		"estado": true
	},
	{
		"nroDocumento": "39875579",
		"tipoPersona": "",
		"tipoDocumento": {
			"value": 80,
			"label": "CUIT"
		},
		"idPersona": "",
		"razonSocial": "BANCO SAFRA S.A.",
		"calle": "Av. San Martin",
		"nro": "998",
		"piso": "",
		"depto": "",
		"sector": "",
		"torre": "",
		"manzana": "",
		"localidad": "CABA",
		"codigoPostal": "",
		"nombreContacto": "Reinaldo Pepe",
		"email": "pepe@gmail.com",
		"telefono": "47484748",
		"nroIngBruto": "",
		"dateStart": "",
		"gln": "",
		"codigoInterno": "",
		"estado": true
	}
]